Workbook

Sheet Resumo
B2: MUSA — Prospecção (parceiros, investidores e museus-piloto)
B3: Gerado em out/2026. Regra de uso: prioridade Alta primeiro; e-mail frio em docs/pitch/email-frio.md + one-pager em anexo.
B5: Aba | C5: Total de alvos
B6: Incubadoras / aceleradoras | C6: =COUNTA(Incubadoras!A2:A100)
B7: Fundos seed | C7: =COUNTA(Fundos!A2:A100)
B8: Museus-piloto | C8: =COUNTA(Museus!A2:A100)
B9: Total | C9: =C6+C7+C8
B10: Já contatados | C10: =COUNTIF(Incubadoras!H2:H100,"Contatado")+COUNTIF(Fundos!H2:H100,"Contatado")+COUNTIF(Museus!H2:H100,"Contatado")
B11: Reuniões marcadas | C11: =COUNTIF(Incubadoras!H2:H100,"Reunião marcada")+COUNTIF(Fundos!H2:H100,"Reunião marcada")+COUNTIF(Museus!H2:H100,"Reunião marcada")

Sheet Incubadoras
A1: Nome | B1: Tipo / Modelo | C1: Site | D1: Contato | E1: Cidade/UF | F1: Fit para o MUSA | G1: Prioridade | H1: Status | I1: Último contato | J1: Próximo passo | K1: Source Name | L1: Source URL
A2: InovAtiva Brasil | B2: Aceleração pública (MDIC), gratuita, equity-free | C2: https://www.inovativa.online | D2: site do programa (pré-inscrição) | E2: Brasil (online) | F2: Gratuito, sem equity; trilha de impacto cabe ao MUSA; dois ciclos/ano — verificar janela de inscrição | G2: Alta | H2: Não contatado | J2: D0: e-mail frio + one-pager → D4: follow-up → D10: LinkedIn | K2: Anprotec — InovAtiva 2025 | L2: https://anprotec.org.br/site/2025/01/inovativa-brasil-abre-pre-inscricoes-para-o-ciclo-de-aceleracao-2025/
A3: Darwin Startups | B3: Aceleradora privada com capital semente | C3: https://darwinstartups.com | D3: site do programa | E3: Florianópolis/SC | F3: Tese B2B tech; investimento direto + mentoria hands-on | G3: Alta | H3: Não contatado | J3: D0: e-mail frio + one-pager → D4: follow-up → D10: LinkedIn | K3: Awisee — Melhores incubadoras/aceleradoras Brasil 2025 | L3: https://awisee.com/br/blog/incubadoras-aceleradoras-startups-brasil/
A4: WOW Aceleradora | B4: Aceleradora + rede de 300 anjos | C4: https://wow.ac | D4: contato@wow.ac | E4: São Paulo/SP | F4: Combina capital semente com mentoria; aceita early stage | G4: Alta | H4: Não contatado | J4: D0: e-mail frio + one-pager → D4: follow-up → D10: LinkedIn | K4: Failory — Top VC Firms in Brazil (2026) | L4: https://www.failory.com/blog/venture-capital-firms-brazil
A5: Tecnopuc Startups (PUCRS) | B5: Incubadora universitária / parque tecnológico | C5: https://pucrs.br/tecnopuc | D5: site do programa | E5: Porto Alegre/RS | F5: Incubadora consolidada; editais e conexão academia-mercado | G5: Média | H5: Não contatado | J5: D0: e-mail frio + one-pager → D4: follow-up → D10: LinkedIn | K5: Awisee — Melhores incubadoras/aceleradoras Brasil 2025 | L5: https://awisee.com/br/blog/incubadoras-aceleradoras-startups-brasil/
A6: ACE Startups | B6: Aceleradora (growth, rede de 200+ investidores) | C6: https://ace.vc | D6: site do programa | E6: São Paulo/SP | F6: Forte rede de investidores para a rodada seguinte | G6: Média | H6: Não contatado | J6: D0: e-mail frio + one-pager → D4: follow-up → D10: LinkedIn | K6: Editorialge — Top aceleradoras LatAm 2025 | L6: https://es.editorialge.com/aceleradoras-startups-latinoamerica/
A7: FCJ Venture Builder | B7: Venture builder | C7: https://fcjventurebuilder.com | D7: site do programa | E7: São Paulo/SP | F7: Co-construção com financiamento inicial; foco em AI/tech | G7: Média | H7: Não contatado | J7: D0: e-mail frio + one-pager → D4: follow-up → D10: LinkedIn | K7: Editorialge — Top aceleradoras LatAm 2025 | L7: https://es.editorialge.com/aceleradoras-startups-latinoamerica/
A8: Wayra Brasil (Telefônica) | B8: Hub de inovação corporativa | C8: https://wayra.com.br | D8: site do programa | E8: São Paulo/SP | F8: Foco AI/IoT; acesso à rede Telefónica para pilotos | G8: Média | H8: Não contatado | J8: D0: e-mail frio + one-pager → D4: follow-up → D10: LinkedIn | K8: Editorialge — Top aceleradoras LatAm 2025 | L8: https://es.editorialge.com/aceleradoras-startups-latinoamerica/
A9: Google for Startups Accelerator LatAm | B9: Aceleradora equity-free (3 meses) | C9: https://startup.google.com/programs/accelerator/ | D9: site do programa | E9: LatAm (online) | F9: AI/cloud/UX; equity-free; bom para a camada de IA do MUSA | G9: Média | H9: Não contatado | J9: D0: e-mail frio + one-pager → D4: follow-up → D10: LinkedIn | K9: Editorialge — Top aceleradoras LatAm 2025 | L9: https://es.editorialge.com/aceleradoras-startups-latinoamerica/
A10: Founder Institute Brasil | B10: Aceleradora pre-seed (4 meses) | C10: https://fi.co | D10: site do programa | E10: São Paulo/SP | F10: Setor-agnóstico, pre-seed; rede global de alumni | G10: Baixa | H10: Não contatado | J10: D0: e-mail frio + one-pager → D4: follow-up → D10: LinkedIn | K10: Editorialge — Top aceleradoras LatAm 2025 | L10: https://es.editorialge.com/aceleradoras-startups-latinoamerica/

Sheet Fundos
A1: Nome | B1: Tipo / Modelo | C1: Site | D1: Contato | E1: Cidade/UF | F1: Fit para o MUSA | G1: Prioridade | H1: Status | I1: Último contato | J1: Próximo passo | K1: Source Name | L1: Source URL
A2: Bossa Invest | B2: VC pre-seed/seed, SaaS B2B | C2: https://bossainvest.com | D2: acesso@bossainvest.com | E2: São Paulo/SP | F2: Foco em SaaS B2B com receita recorrente — exatamente o modelo MUSA | G2: Alta | H2: Não contatado | J2: D0: e-mail frio + one-pager → D4: follow-up → D10: LinkedIn | K2: Failory — Top VC Firms in Brazil (2026) | L2: https://www.failory.com/blog/venture-capital-firms-brazil
A3: DOMO.VC | B3: VC early stage/seed | C3: https://domo.vc | D3: contato@domo.vc | E3: São Paulo/SP | F3: Histórico de early checks vencedores (Loggi, Gympass, Hotmart) | G3: Alta | H3: Não contatado | J3: D0: e-mail frio + one-pager → D4: follow-up → D10: LinkedIn | K3: Failory — Top VC Firms in Brazil (2026) | L3: https://www.failory.com/blog/venture-capital-firms-brazil
A4: ONEVC | B4: VC seed, portfólio concentrado | C4: https://onevc.vc | D4: via site | E4: São Paulo/SP | F4: Suporte hands-on em recrutamento tech — útil para escalar a equipe | G4: Alta | H4: Não contatado | J4: D0: e-mail frio + one-pager → D4: follow-up → D10: LinkedIn | K4: Failory — Top VC Firms in Brazil (2026) | L4: https://www.failory.com/blog/venture-capital-firms-brazil
A5: Latitud | B5: VC pre-seed/seed + plataforma | C5: https://latitud.com | D5: ventures@latitud.com | E5: São Paulo/SP | F5: Pre-seed hands-on para founders LatAm | G5: Média | H5: Não contatado | J5: D0: e-mail frio + one-pager → D4: follow-up → D10: LinkedIn | K5: Failory — Top VC Firms in Brazil (2026) | L5: https://www.failory.com/blog/venture-capital-firms-brazil
A6: Atlantico | B6: VC early stage LatAm | C6: https://atlantico.vc | D6: via site | E6: São Paulo/SP | F6: Tese de economia digital LatAm; hands-on (Kavak, Loft) | G6: Média | H6: Não contatado | J6: D0: e-mail frio + one-pager → D4: follow-up → D10: LinkedIn | K6: Failory — Top VC Firms in Brazil (2026) | L6: https://www.failory.com/blog/venture-capital-firms-brazil
A7: Indicator Capital | B7: VC seed, IoT/tech, B Corp | C7: https://indicatorcapital.com | D7: contact@indicatorcapital.com | E7: São Paulo/SP | F7: Tese IoT/hardware conversa com totens e escaneamento 3D | G7: Média | H7: Não contatado | J7: D0: e-mail frio + one-pager → D4: follow-up → D10: LinkedIn | K7: Failory — Top VC Firms in Brazil (2026) | L7: https://www.failory.com/blog/venture-capital-firms-brazil
A8: DGF Investimentos | B8: VC B2B software, early stage | C8: https://dgf.com.br | D8: startups@dgf.com.br | E8: São Paulo/SP | F8: Foco B2B software; exits RD Station e Reclame Aqui | G8: Média | H8: Não contatado | J8: D0: e-mail frio + one-pager → D4: follow-up → D10: LinkedIn | K8: Failory — Top VC Firms in Brazil (2026) | L8: https://www.failory.com/blog/venture-capital-firms-brazil
A9: Mindset Ventures | B9: VC early stage B2B | C9: https://mindset.ventures | D9: contact.mindsetventures@gmail.com | E9: São Paulo/SP | F9: B2B com suporte a expansão internacional | G9: Baixa | H9: Não contatado | J9: D0: e-mail frio + one-pager → D4: follow-up → D10: LinkedIn | K9: Failory — Top VC Firms in Brazil (2026) | L9: https://www.failory.com/blog/venture-capital-firms-brazil
A10: Westwood Capital | B10: Gestora seed (parceira da Quintal Ventures/RIC) | C10: https://westwoodcapital.com.br | D10: via site | E10: Curitiba/PR | F10: Entre os fundos seed mais ativos do Brasil em 2025 (LAVCA) | G10: Média | H10: Não contatado | J10: D0: e-mail frio + one-pager → D4: follow-up → D10: LinkedIn | K10: TOPVIEW — LAVCA Emerging Tech Hub 2025 | L10: https://topview.com.br/grands/estudo-aponta-curitiba-como-polo-emergente-de-inovacao-e-tecnologia-na-america-latina/
A11: Kaszek | B11: VC (seed a growth) | C11: https://kaszek.com | D11: via site | E11: São Paulo/SP | F11: Maior fundo da região; entraria melhor numa rodada posterior | G11: Baixa | H11: Não contatado | J11: D0: e-mail frio + one-pager → D4: follow-up → D10: LinkedIn | K11: Dicas Globais — startups BR 2025 | L11: https://dicasglobais.com/startups-brasileiras-inovando-2025/
A12: Monashees | B12: VC (seed a growth) | C12: https://monashees.com.br | D12: via site | E12: São Paulo/SP | F12: Fundo tier-1 BR; também mais adiante no funil | G12: Baixa | H12: Não contatado | J12: D0: e-mail frio + one-pager → D4: follow-up → D10: LinkedIn | K12: Dicas Globais — startups BR 2025 | L12: https://dicasglobais.com/startups-brasileiras-inovando-2025/

Sheet Museus
A1: Nome | B1: Tipo / Modelo | C1: Site | D1: Contato | E1: Cidade/UF | F1: Fit para o MUSA | G1: Prioridade | H1: Status | I1: Último contato | J1: Próximo passo | K1: Source Name | L1: Source URL
A2: Museu do Diamante | B2: Museu federal (Ibram), histórico | D2: site/telefone institucional | E2: Diamantina/MG | F2: Cidade histórica turística; acervo valioso e público visitante do circuito das serras | G2: Alta | H2: Não contatado | J2: D0: e-mail/telefone à diretoria → D7: follow-up → D15: visita ou chamada | K2: Wikipédia — Instituto Brasileiro de Museus (museus federais) | L2: https://pt.wikipedia.org/wiki/Instituto_Brasileiro_de_Museus
A3: Museu do Ouro | B3: Museu federal (Ibram), histórico | D3: site/telefone institucional | E3: Sabará/MG | F3: Eixo do turismo histórico de MG; acervo de arte sacra e ourivesaria | G3: Alta | H3: Não contatado | J3: D0: e-mail/telefone à diretoria → D7: follow-up → D15: visita ou chamada | K3: Wikipédia — Instituto Brasileiro de Museus (museus federais) | L3: https://pt.wikipedia.org/wiki/Instituto_Brasileiro_de_Museus
A4: Museu Regional de Caetano | B4: Museu federal (Ibram), regional | D4: site/telefone institucional | E4: Caetano/MG | F4: Pequeno porte, sem equipe técnica — perfil exato do plano Bronze | G4: Média | H4: Não contatado | J4: D0: e-mail/telefone à diretoria → D7: follow-up → D15: visita ou chamada | K4: Wikipédia — Instituto Brasileiro de Museus (museus federais) | L4: https://pt.wikipedia.org/wiki/Instituto_Brasileiro_de_Museus
A5: Museu das Missões | B5: Museu federal (Ibram), sítio histórico | D5: site/telefone institucional | E5: São Miguel das Missões/RS | F5: Sítio arqueológico jesuítico; 3D e gêmeo digital têm apelo forte | G5: Alta | H5: Não contatado | J5: D0: e-mail/telefone à diretoria → D7: follow-up → D15: visita ou chamada | K5: Wikipédia — Instituto Brasileiro de Museus (museus federais) | L5: https://pt.wikipedia.org/wiki/Instituto_Brasileiro_de_Museus
A6: Museu das Bandeiras | B6: Museu federal (Ibram), histórico | D6: site/telefone institucional | E6: Goiânia/GO | F6: Acervo bandeirista; capital com turismo cultural crescente | G6: Média | H6: Não contatado | J6: D0: e-mail/telefone à diretoria → D7: follow-up → D15: visita ou chamada | K6: Wikipédia — Instituto Brasileiro de Museus (museus federais) | L6: https://pt.wikipedia.org/wiki/Instituto_Brasileiro_de_Museus
A7: Museu de Arte Sacra da Igreja da Boa Morte | B7: Museu federal (Ibram), arte sacra | D7: site/telefone institucional | E7: Goiás/GO | F7: Cidade histórica; arte sacra fotografável, bom showcase do pipeline | G7: Média | H7: Não contatado | J7: D0: e-mail/telefone à diretoria → D7: follow-up → D15: visita ou chamada | K7: Wikipédia — Instituto Brasileiro de Museus (museus federais) | L7: https://pt.wikipedia.org/wiki/Instituto_Brasileiro_de_Museus
A8: Museu de Arte Religiosa e Tradicional de Cabo Frio | B8: Museu federal (Ibram) | D8: site/telefone institucional | E8: Cabo Frio/RJ | F8: Cidade turística de praia + patrimônio; sinergia de público | G8: Média | H8: Não contatado | J8: D0: e-mail/telefone à diretoria → D7: follow-up → D15: visita ou chamada | K8: Wikipédia — Instituto Brasileiro de Museus (museus federais) | L8: https://pt.wikipedia.org/wiki/Instituto_Brasileiro_de_Museus
A9: Museu Forte Defensor Pérpetuo | B9: Museu federal (Ibram), forte histórico | D9: site/telefone institucional | E9: Paraty/RJ | F9: Paraty é destino cultural internacional; forte + vilarejo pedem 3D | G9: Alta | H9: Não contatado | J9: D0: e-mail/telefone à diretoria → D7: follow-up → D15: visita ou chamada | K9: Wikipédia — Instituto Brasileiro de Museus (museus federais) | L9: https://pt.wikipedia.org/wiki/Instituto_Brasileiro_de_Museus
A10: Museu Histórico e Artístico do Maranhão | B10: Museu estadual, histórico | D10: site/telefone institucional | E10: São Luís/MA | F10: Centro histórico Patrimônio Mundial UNESCO; acervo de mobiliário e arte | G10: Alta | H10: Não contatado | J10: D0: e-mail/telefone à diretoria → D7: follow-up → D15: visita ou chamada | K10: Ibram — Museus em Números / plataforma Museus BR (2024) | L10: https://agenciagov.ebc.com.br/noticias/202401/ibram-celebra-15-anos-neste-sabado-20-e-lanca-a-plataforma-nova-museus-br
A11: Museu da Borracha Governador Hélio M. da Costa | B11: Museu estadual, histórico | D11: site/telefone institucional | E11: Rio Branco/AC | F11: Memória seringal; digitalização ampliaria alcance de região remota | G11: Baixa | H11: Não contatado | J11: D0: e-mail/telefone à diretoria → D7: follow-up → D15: visita ou chamada | K11: Ibram — Museus em Números / plataforma Museus BR (2024) | L11: https://agenciagov.ebc.com.br/noticias/202401/ibram-celebra-15-anos-neste-sabado-20-e-lanca-a-plataforma-nova-museus-br
A12: Museu Socioambiental de Itaipu | B12: Museu temático (Itaipu Binacional) | D12: site/telefone institucional | E12: Niterói/RJ | F12: Museu socioambiental; perfil de patrocínio corporativo possível | G12: Baixa | H12: Não contatado | J12: D0: e-mail/telefone à diretoria → D7: follow-up → D15: visita ou chamada | K12: Wikipédia — Instituto Brasileiro de Museus (museus federais) | L12: https://pt.wikipedia.org/wiki/Instituto_Brasileiro_de_Museus

Sheet Funil semanal
B2: Funil semanal — acompanhamento
B3: As linhas de status contam AO VIVO das abas Incubadoras/Fundos/Museus. Para congelar o histórico: ao fechar a semana, copie a linha e Cole especial → Valores.
B5: Semana de | C5: Não contatado | D5: Contatado | E5: Respondeu | F5: Reunião marcada | G5: Proposta enviada | H5: Fechado | I5: Descartado | J5: Total em cadastro | K5: Observações
C6: =COUNTIF(Incubadoras!$H$2:$H$100,C$5)+COUNTIF(Fundos!$H$2:$H$100,C$5)+COUNTIF(Museus!$H$2:$H$100,C$5) | D6: =COUNTIF(Incubadoras!$H$2:$H$100,D$5)+COUNTIF(Fundos!$H$2:$H$100,D$5)+COUNTIF(Museus!$H$2:$H$100,D$5) | E6: =COUNTIF(Incubadoras!$H$2:$H$100,E$5)+COUNTIF(Fundos!$H$2:$H$100,E$5)+COUNTIF(Museus!$H$2:$H$100,E$5) | F6: =COUNTIF(Incubadoras!$H$2:$H$100,F$5)+COUNTIF(Fundos!$H$2:$H$100,F$5)+COUNTIF(Museus!$H$2:$H$100,F$5) | G6: =COUNTIF(Incubadoras!$H$2:$H$100,G$5)+COUNTIF(Fundos!$H$2:$H$100,G$5)+COUNTIF(Museus!$H$2:$H$100,G$5) | H6: =COUNTIF(Incubadoras!$H$2:$H$100,H$5)+COUNTIF(Fundos!$H$2:$H$100,H$5)+COUNTIF(Museus!$H$2:$H$100,H$5) | I6: =COUNTIF(Incubadoras!$H$2:$H$100,I$5)+COUNTIF(Fundos!$H$2:$H$100,I$5)+COUNTIF(Museus!$H$2:$H$100,I$5) | J6: =COUNTA(Incubadoras!$A$2:$A$100)+COUNTA(Fundos!$A$2:$A$100)+COUNTA(Museus!$A$2:$A$100)
C7: =COUNTIF(Incubadoras!$H$2:$H$100,C$5)+COUNTIF(Fundos!$H$2:$H$100,C$5)+COUNTIF(Museus!$H$2:$H$100,C$5) | D7: =COUNTIF(Incubadoras!$H$2:$H$100,D$5)+COUNTIF(Fundos!$H$2:$H$100,D$5)+COUNTIF(Museus!$H$2:$H$100,D$5) | E7: =COUNTIF(Incubadoras!$H$2:$H$100,E$5)+COUNTIF(Fundos!$H$2:$H$100,E$5)+COUNTIF(Museus!$H$2:$H$100,E$5) | F7: =COUNTIF(Incubadoras!$H$2:$H$100,F$5)+COUNTIF(Fundos!$H$2:$H$100,F$5)+COUNTIF(Museus!$H$2:$H$100,F$5) | G7: =COUNTIF(Incubadoras!$H$2:$H$100,G$5)+COUNTIF(Fundos!$H$2:$H$100,G$5)+COUNTIF(Museus!$H$2:$H$100,G$5) | H7: =COUNTIF(Incubadoras!$H$2:$H$100,H$5)+COUNTIF(Fundos!$H$2:$H$100,H$5)+COUNTIF(Museus!$H$2:$H$100,H$5) | I7: =COUNTIF(Incubadoras!$H$2:$H$100,I$5)+COUNTIF(Fundos!$H$2:$H$100,I$5)+COUNTIF(Museus!$H$2:$H$100,I$5) | J7: =COUNTA(Incubadoras!$A$2:$A$100)+COUNTA(Fundos!$A$2:$A$100)+COUNTA(Museus!$A$2:$A$100)
C8: =COUNTIF(Incubadoras!$H$2:$H$100,C$5)+COUNTIF(Fundos!$H$2:$H$100,C$5)+COUNTIF(Museus!$H$2:$H$100,C$5) | D8: =COUNTIF(Incubadoras!$H$2:$H$100,D$5)+COUNTIF(Fundos!$H$2:$H$100,D$5)+COUNTIF(Museus!$H$2:$H$100,D$5) | E8: =COUNTIF(Incubadoras!$H$2:$H$100,E$5)+COUNTIF(Fundos!$H$2:$H$100,E$5)+COUNTIF(Museus!$H$2:$H$100,E$5) | F8: =COUNTIF(Incubadoras!$H$2:$H$100,F$5)+COUNTIF(Fundos!$H$2:$H$100,F$5)+COUNTIF(Museus!$H$2:$H$100,F$5) | G8: =COUNTIF(Incubadoras!$H$2:$H$100,G$5)+COUNTIF(Fundos!$H$2:$H$100,G$5)+COUNTIF(Museus!$H$2:$H$100,G$5) | H8: =COUNTIF(Incubadoras!$H$2:$H$100,H$5)+COUNTIF(Fundos!$H$2:$H$100,H$5)+COUNTIF(Museus!$H$2:$H$100,H$5) | I8: =COUNTIF(Incubadoras!$H$2:$H$100,I$5)+COUNTIF(Fundos!$H$2:$H$100,I$5)+COUNTIF(Museus!$H$2:$H$100,I$5) | J8: =COUNTA(Incubadoras!$A$2:$A$100)+COUNTA(Fundos!$A$2:$A$100)+COUNTA(Museus!$A$2:$A$100)
C9: =COUNTIF(Incubadoras!$H$2:$H$100,C$5)+COUNTIF(Fundos!$H$2:$H$100,C$5)+COUNTIF(Museus!$H$2:$H$100,C$5) | D9: =COUNTIF(Incubadoras!$H$2:$H$100,D$5)+COUNTIF(Fundos!$H$2:$H$100,D$5)+COUNTIF(Museus!$H$2:$H$100,D$5) | E9: =COUNTIF(Incubadoras!$H$2:$H$100,E$5)+COUNTIF(Fundos!$H$2:$H$100,E$5)+COUNTIF(Museus!$H$2:$H$100,E$5) | F9: =COUNTIF(Incubadoras!$H$2:$H$100,F$5)+COUNTIF(Fundos!$H$2:$H$100,F$5)+COUNTIF(Museus!$H$2:$H$100,F$5) | G9: =COUNTIF(Incubadoras!$H$2:$H$100,G$5)+COUNTIF(Fundos!$H$2:$H$100,G$5)+COUNTIF(Museus!$H$2:$H$100,G$5) | H9: =COUNTIF(Incubadoras!$H$2:$H$100,H$5)+COUNTIF(Fundos!$H$2:$H$100,H$5)+COUNTIF(Museus!$H$2:$H$100,H$5) | I9: =COUNTIF(Incubadoras!$H$2:$H$100,I$5)+COUNTIF(Fundos!$H$2:$H$100,I$5)+COUNTIF(Museus!$H$2:$H$100,I$5) | J9: =COUNTA(Incubadoras!$A$2:$A$100)+COUNTA(Fundos!$A$2:$A$100)+COUNTA(Museus!$A$2:$A$100)
C10: =COUNTIF(Incubadoras!$H$2:$H$100,C$5)+COUNTIF(Fundos!$H$2:$H$100,C$5)+COUNTIF(Museus!$H$2:$H$100,C$5) | D10: =COUNTIF(Incubadoras!$H$2:$H$100,D$5)+COUNTIF(Fundos!$H$2:$H$100,D$5)+COUNTIF(Museus!$H$2:$H$100,D$5) | E10: =COUNTIF(Incubadoras!$H$2:$H$100,E$5)+COUNTIF(Fundos!$H$2:$H$100,E$5)+COUNTIF(Museus!$H$2:$H$100,E$5) | F10: =COUNTIF(Incubadoras!$H$2:$H$100,F$5)+COUNTIF(Fundos!$H$2:$H$100,F$5)+COUNTIF(Museus!$H$2:$H$100,F$5) | G10: =COUNTIF(Incubadoras!$H$2:$H$100,G$5)+COUNTIF(Fundos!$H$2:$H$100,G$5)+COUNTIF(Museus!$H$2:$H$100,G$5) | H10: =COUNTIF(Incubadoras!$H$2:$H$100,H$5)+COUNTIF(Fundos!$H$2:$H$100,H$5)+COUNTIF(Museus!$H$2:$H$100,H$5) | I10: =COUNTIF(Incubadoras!$H$2:$H$100,I$5)+COUNTIF(Fundos!$H$2:$H$100,I$5)+COUNTIF(Museus!$H$2:$H$100,I$5) | J10: =COUNTA(Incubadoras!$A$2:$A$100)+COUNTA(Fundos!$A$2:$A$100)+COUNTA(Museus!$A$2:$A$100)
C11: =COUNTIF(Incubadoras!$H$2:$H$100,C$5)+COUNTIF(Fundos!$H$2:$H$100,C$5)+COUNTIF(Museus!$H$2:$H$100,C$5) | D11: =COUNTIF(Incubadoras!$H$2:$H$100,D$5)+COUNTIF(Fundos!$H$2:$H$100,D$5)+COUNTIF(Museus!$H$2:$H$100,D$5) | E11: =COUNTIF(Incubadoras!$H$2:$H$100,E$5)+COUNTIF(Fundos!$H$2:$H$100,E$5)+COUNTIF(Museus!$H$2:$H$100,E$5) | F11: =COUNTIF(Incubadoras!$H$2:$H$100,F$5)+COUNTIF(Fundos!$H$2:$H$100,F$5)+COUNTIF(Museus!$H$2:$H$100,F$5) | G11: =COUNTIF(Incubadoras!$H$2:$H$100,G$5)+COUNTIF(Fundos!$H$2:$H$100,G$5)+COUNTIF(Museus!$H$2:$H$100,G$5) | H11: =COUNTIF(Incubadoras!$H$2:$H$100,H$5)+COUNTIF(Fundos!$H$2:$H$100,H$5)+COUNTIF(Museus!$H$2:$H$100,H$5) | I11: =COUNTIF(Incubadoras!$H$2:$H$100,I$5)+COUNTIF(Fundos!$H$2:$H$100,I$5)+COUNTIF(Museus!$H$2:$H$100,I$5) | J11: =COUNTA(Incubadoras!$A$2:$A$100)+COUNTA(Fundos!$A$2:$A$100)+COUNTA(Museus!$A$2:$A$100)
C12: =COUNTIF(Incubadoras!$H$2:$H$100,C$5)+COUNTIF(Fundos!$H$2:$H$100,C$5)+COUNTIF(Museus!$H$2:$H$100,C$5) | D12: =COUNTIF(Incubadoras!$H$2:$H$100,D$5)+COUNTIF(Fundos!$H$2:$H$100,D$5)+COUNTIF(Museus!$H$2:$H$100,D$5) | E12: =COUNTIF(Incubadoras!$H$2:$H$100,E$5)+COUNTIF(Fundos!$H$2:$H$100,E$5)+COUNTIF(Museus!$H$2:$H$100,E$5) | F12: =COUNTIF(Incubadoras!$H$2:$H$100,F$5)+COUNTIF(Fundos!$H$2:$H$100,F$5)+COUNTIF(Museus!$H$2:$H$100,F$5) | G12: =COUNTIF(Incubadoras!$H$2:$H$100,G$5)+COUNTIF(Fundos!$H$2:$H$100,G$5)+COUNTIF(Museus!$H$2:$H$100,G$5) | H12: =COUNTIF(Incubadoras!$H$2:$H$100,H$5)+COUNTIF(Fundos!$H$2:$H$100,H$5)+COUNTIF(Museus!$H$2:$H$100,H$5) | I12: =COUNTIF(Incubadoras!$H$2:$H$100,I$5)+COUNTIF(Fundos!$H$2:$H$100,I$5)+COUNTIF(Museus!$H$2:$H$100,I$5) | J12: =COUNTA(Incubadoras!$A$2:$A$100)+COUNTA(Fundos!$A$2:$A$100)+COUNTA(Museus!$A$2:$A$100)
C13: =COUNTIF(Incubadoras!$H$2:$H$100,C$5)+COUNTIF(Fundos!$H$2:$H$100,C$5)+COUNTIF(Museus!$H$2:$H$100,C$5) | D13: =COUNTIF(Incubadoras!$H$2:$H$100,D$5)+COUNTIF(Fundos!$H$2:$H$100,D$5)+COUNTIF(Museus!$H$2:$H$100,D$5) | E13: =COUNTIF(Incubadoras!$H$2:$H$100,E$5)+COUNTIF(Fundos!$H$2:$H$100,E$5)+COUNTIF(Museus!$H$2:$H$100,E$5) | F13: =COUNTIF(Incubadoras!$H$2:$H$100,F$5)+COUNTIF(Fundos!$H$2:$H$100,F$5)+COUNTIF(Museus!$H$2:$H$100,F$5) | G13: =COUNTIF(Incubadoras!$H$2:$H$100,G$5)+COUNTIF(Fundos!$H$2:$H$100,G$5)+COUNTIF(Museus!$H$2:$H$100,G$5) | H13: =COUNTIF(Incubadoras!$H$2:$H$100,H$5)+COUNTIF(Fundos!$H$2:$H$100,H$5)+COUNTIF(Museus!$H$2:$H$100,H$5) | I13: =COUNTIF(Incubadoras!$H$2:$H$100,I$5)+COUNTIF(Fundos!$H$2:$H$100,I$5)+COUNTIF(Museus!$H$2:$H$100,I$5) | J13: =COUNTA(Incubadoras!$A$2:$A$100)+COUNTA(Fundos!$A$2:$A$100)+COUNTA(Museus!$A$2:$A$100)
C14: =COUNTIF(Incubadoras!$H$2:$H$100,C$5)+COUNTIF(Fundos!$H$2:$H$100,C$5)+COUNTIF(Museus!$H$2:$H$100,C$5) | D14: =COUNTIF(Incubadoras!$H$2:$H$100,D$5)+COUNTIF(Fundos!$H$2:$H$100,D$5)+COUNTIF(Museus!$H$2:$H$100,D$5) | E14: =COUNTIF(Incubadoras!$H$2:$H$100,E$5)+COUNTIF(Fundos!$H$2:$H$100,E$5)+COUNTIF(Museus!$H$2:$H$100,E$5) | F14: =COUNTIF(Incubadoras!$H$2:$H$100,F$5)+COUNTIF(Fundos!$H$2:$H$100,F$5)+COUNTIF(Museus!$H$2:$H$100,F$5) | G14: =COUNTIF(Incubadoras!$H$2:$H$100,G$5)+COUNTIF(Fundos!$H$2:$H$100,G$5)+COUNTIF(Museus!$H$2:$H$100,G$5) | H14: =COUNTIF(Incubadoras!$H$2:$H$100,H$5)+COUNTIF(Fundos!$H$2:$H$100,H$5)+COUNTIF(Museus!$H$2:$H$100,H$5) | I14: =COUNTIF(Incubadoras!$H$2:$H$100,I$5)+COUNTIF(Fundos!$H$2:$H$100,I$5)+COUNTIF(Museus!$H$2:$H$100,I$5) | J14: =COUNTA(Incubadoras!$A$2:$A$100)+COUNTA(Fundos!$A$2:$A$100)+COUNTA(Museus!$A$2:$A$100)
C15: =COUNTIF(Incubadoras!$H$2:$H$100,C$5)+COUNTIF(Fundos!$H$2:$H$100,C$5)+COUNTIF(Museus!$H$2:$H$100,C$5) | D15: =COUNTIF(Incubadoras!$H$2:$H$100,D$5)+COUNTIF(Fundos!$H$2:$H$100,D$5)+COUNTIF(Museus!$H$2:$H$100,D$5) | E15: =COUNTIF(Incubadoras!$H$2:$H$100,E$5)+COUNTIF(Fundos!$H$2:$H$100,E$5)+COUNTIF(Museus!$H$2:$H$100,E$5) | F15: =COUNTIF(Incubadoras!$H$2:$H$100,F$5)+COUNTIF(Fundos!$H$2:$H$100,F$5)+COUNTIF(Museus!$H$2:$H$100,F$5) | G15: =COUNTIF(Incubadoras!$H$2:$H$100,G$5)+COUNTIF(Fundos!$H$2:$H$100,G$5)+COUNTIF(Museus!$H$2:$H$100,G$5) | H15: =COUNTIF(Incubadoras!$H$2:$H$100,H$5)+COUNTIF(Fundos!$H$2:$H$100,H$5)+COUNTIF(Museus!$H$2:$H$100,H$5) | I15: =COUNTIF(Incubadoras!$H$2:$H$100,I$5)+COUNTIF(Fundos!$H$2:$H$100,I$5)+COUNTIF(Museus!$H$2:$H$100,I$5) | J15: =COUNTA(Incubadoras!$A$2:$A$100)+COUNTA(Fundos!$A$2:$A$100)+COUNTA(Museus!$A$2:$A$100)
C16: =COUNTIF(Incubadoras!$H$2:$H$100,C$5)+COUNTIF(Fundos!$H$2:$H$100,C$5)+COUNTIF(Museus!$H$2:$H$100,C$5) | D16: =COUNTIF(Incubadoras!$H$2:$H$100,D$5)+COUNTIF(Fundos!$H$2:$H$100,D$5)+COUNTIF(Museus!$H$2:$H$100,D$5) | E16: =COUNTIF(Incubadoras!$H$2:$H$100,E$5)+COUNTIF(Fundos!$H$2:$H$100,E$5)+COUNTIF(Museus!$H$2:$H$100,E$5) | F16: =COUNTIF(Incubadoras!$H$2:$H$100,F$5)+COUNTIF(Fundos!$H$2:$H$100,F$5)+COUNTIF(Museus!$H$2:$H$100,F$5) | G16: =COUNTIF(Incubadoras!$H$2:$H$100,G$5)+COUNTIF(Fundos!$H$2:$H$100,G$5)+COUNTIF(Museus!$H$2:$H$100,G$5) | H16: =COUNTIF(Incubadoras!$H$2:$H$100,H$5)+COUNTIF(Fundos!$H$2:$H$100,H$5)+COUNTIF(Museus!$H$2:$H$100,H$5) | I16: =COUNTIF(Incubadoras!$H$2:$H$100,I$5)+COUNTIF(Fundos!$H$2:$H$100,I$5)+COUNTIF(Museus!$H$2:$H$100,I$5) | J16: =COUNTA(Incubadoras!$A$2:$A$100)+COUNTA(Fundos!$A$2:$A$100)+COUNTA(Museus!$A$2:$A$100)
C17: =COUNTIF(Incubadoras!$H$2:$H$100,C$5)+COUNTIF(Fundos!$H$2:$H$100,C$5)+COUNTIF(Museus!$H$2:$H$100,C$5) | D17: =COUNTIF(Incubadoras!$H$2:$H$100,D$5)+COUNTIF(Fundos!$H$2:$H$100,D$5)+COUNTIF(Museus!$H$2:$H$100,D$5) | E17: =COUNTIF(Incubadoras!$H$2:$H$100,E$5)+COUNTIF(Fundos!$H$2:$H$100,E$5)+COUNTIF(Museus!$H$2:$H$100,E$5) | F17: =COUNTIF(Incubadoras!$H$2:$H$100,F$5)+COUNTIF(Fundos!$H$2:$H$100,F$5)+COUNTIF(Museus!$H$2:$H$100,F$5) | G17: =COUNTIF(Incubadoras!$H$2:$H$100,G$5)+COUNTIF(Fundos!$H$2:$H$100,G$5)+COUNTIF(Museus!$H$2:$H$100,G$5) | H17: =COUNTIF(Incubadoras!$H$2:$H$100,H$5)+COUNTIF(Fundos!$H$2:$H$100,H$5)+COUNTIF(Museus!$H$2:$H$100,H$5) | I17: =COUNTIF(Incubadoras!$H$2:$H$100,I$5)+COUNTIF(Fundos!$H$2:$H$100,I$5)+COUNTIF(Museus!$H$2:$H$100,I$5) | J17: =COUNTA(Incubadoras!$A$2:$A$100)+COUNTA(Fundos!$A$2:$A$100)+COUNTA(Museus!$A$2:$A$100)
